{
  "project_info": {
    "project_number": "238643124008",
    "project_id": "dashrider-fda45",
    "storage_bucket": "dashrider-fda45.appspot.com"
  },
  "client": [
    {
      "client_info": {
        "mobilesdk_app_id": "1:238643124008:android:519edbd2977a83838fe21d",
        "android_client_info": {
          "package_name": "main.com.dash"
        }
      },
      "oauth_client": [
        {
          "client_id": "238643124008-pe7plgi406l2sfdg8nd17jhic7ggkkj7.apps.googleusercontent.com",
          "client_type": 1,
          "android_info": {
            "package_name": "main.com.dash",
            "certificate_hash": "27fb8175e6fec77e7b3d1a2e6e1ca5bcaf451153"
          }
        },
        {
          "client_id": "238643124008-pjjs3e5qrhqr93p0r6vlgd1utt5vvrtp.apps.googleusercontent.com",
          "client_type": 3
        }
      ],
      "api_key": [
        {
          "current_key": "AIzaSyDHU78vfsrjtxw_8hf1sQybhpQxWV0T5j4"
        }
      ],
      "services": {
        "appinvite_service": {
          "other_platform_oauth_client": [
            {
              "client_id": "238643124008-pjjs3e5qrhqr93p0r6vlgd1utt5vvrtp.apps.googleusercontent.com",
              "client_type": 3
            }
          ]
        }
      }
    }
  ],
  "configuration_version": "1"
}